mpnp/data_preprocessing.py
mpnp/experiment.py
mpnp/notebook_application.py
mpnp/utilities.py
mpnp-0.1.7.dist-info/LICENSE.txt
mpnp-0.1.7.dist-info/METADATA
mpnp-0.1.7.dist-info/WHEEL
mpnp-0.1.7.dist-info/top_level.txt
mpnp-0.1.7.dist-info/RECORD
